{"cameraMode":{"drawMode":0,"name":"Shaded","section":"Shading Mode"},"sceneLighting":false,"audioPlay":false,"sceneViewState":{"m_AlwaysRefresh":false,"showFog":true,"showSkybox":false,"showFlares":true,"showImageEffects":true,"showParticleSystems":true,"showVisualEffectGraphs":true,"m_FxEnabled":true},"in2DMode":false,"pivot":{"x":642.9596557617188,"y":-690.8080444335938,"z":660.9881591796875},"rotation":{"x":0.2948596477508545,"y":0.36325910687446597,"z":-0.12237928807735443,"w":0.8753734230995178},"size":610.388671875,"orthographic":false}